vdldraw/__init__.py
vdldraw/canvas.py
vdldraw/color.py
vdldraw/convert.py
vdldraw/draw.py
vdldraw/folder.py
vdldraw/configs/plot.mplstyle
vdldraw/configs/rgb.txt
vdldraw-0.1.7.dist-info/LICENSE
vdldraw-0.1.7.dist-info/METADATA
vdldraw-0.1.7.dist-info/WHEEL
vdldraw-0.1.7.dist-info/top_level.txt
vdldraw-0.1.7.dist-info/RECORD
