Metadata-Version: 2.1
Name: vdldraw
Version: 0.1.7
Summary: Batch plot the log files exported from VisualDL using Matplotlib.
Home-page: https://github.com/geoyee/VDLdraw
Author: geoyee
Author-email: geoyee@yeah.net
License: UNKNOWN
Platform: UNKNOWN
Classifier: Programming Language :: Python :: 3
Classifier: Programming Language :: Python :: 3.8
Classifier: License :: OSI Approved :: Apache Software License
Requires-Dist: visualdl
Requires-Dist: matplotlib
Requires-Dist: protobuf
